async_pokepy/__init__.py
async_pokepy/client.py
async_pokepy/exceptions.py
async_pokepy/http.py
async_pokepy/utils.py
async_pokepy/types/__init__.py
async_pokepy/types/abc.py
async_pokepy/types/ability.py
async_pokepy/types/berry.py
async_pokepy/types/common.py
async_pokepy/types/machine.py
async_pokepy/types/move.py
async_pokepy/types/pagination.py
async_pokepy/types/pokemon.py
async_pokepy-0.1.5a0.dist-info/LICENSE
async_pokepy-0.1.5a0.dist-info/METADATA
async_pokepy-0.1.5a0.dist-info/WHEEL
async_pokepy-0.1.5a0.dist-info/top_level.txt
async_pokepy-0.1.5a0.dist-info/RECORD
