Metadata-Version: 2.1
Name: async-pokepy
Version: 0.1.5a0
Summary: A simple asynchronous wrapper for the PokeAPI.co API.
Home-page: https://github.com/PendragonLore/async_pokepy
Author: Lorenzo
License: MIT
Download-URL: https://github.com/PendragonLore/async_pokepy/archive/0.1.5a.tar.gz
Project-URL: Issue Tracker, https://github.com/PendragonLore/async_pokepy/issues
Project-URL: Documentation, https://async-pokepy.rtfd.io
Keywords: async pokemon asyncio rest api
Platform: macOS
Platform: POSIX
Platform: Windows
Classifier: Programming Language :: Python :: 3 :: Only
Classifier: Programming Language :: Python :: 3.5
Classifier: Programming Language :: Python :: 3.6
Classifier: Programming Language :: Python :: 3.7
Classifier: License :: OSI Approved :: MIT License
Classifier: Natural Language :: English
Classifier: Intended Audience :: Developers
Classifier: Topic :: Internet
Classifier: Topic :: Software Development :: Libraries
Classifier: Topic :: Software Development :: Libraries :: Python Modules
Classifier: Topic :: Utilities
Classifier: Framework :: AsyncIO
Classifier: Operating System :: OS Independent
Classifier: Development Status :: 3 - Alpha
Requires-Python: >=3.5.3
Requires-Dist: aiohttp (<3.6.0,>=3.3.0)
Provides-Extra: docs
Requires-Dist: sphinx (==1.7.4) ; extra == 'docs'
Requires-Dist: sphinxcontrib-asyncio ; extra == 'docs'
Provides-Extra: lru
Requires-Dist: lru-dict ; extra == 'lru'
Provides-Extra: tests
Requires-Dist: flake8 ; extra == 'tests'
Requires-Dist: pylint ; extra == 'tests'
Requires-Dist: pytest ; extra == 'tests'
Requires-Dist: pytest-cov ; extra == 'tests'
Requires-Dist: isort ; extra == 'tests'
